MANIFEST.in
README.rst
setup.py
tests/__init__.py
tests/test_process.py
tests/test_validate.py
tests/conf/__init__.py
tests/conf/test_parse_namelist.py
wrfconf/__init__.py
wrfconf/cli.py
wrfconf/process.py
wrfconf/utils.py
wrfconf/validate.py
wrfconf/version.py
wrfconf.egg-info/PKG-INFO
wrfconf.egg-info/SOURCES.txt
wrfconf.egg-info/dependency_links.txt
wrfconf.egg-info/entry_points.txt
wrfconf.egg-info/not-zip-safe
wrfconf.egg-info/requires.txt
wrfconf.egg-info/top_level.txt
wrfconf/conf/__init__.py
wrfconf/conf/parse_namelist.py
wrfconf/serialize/__init__.py
wrfconf/serialize/nodes.py
wrfconf/serialize/representer.py
wrfconf/serialize/serializer.py