Metadata-Version: 1.1
Name: wrfconf
Version: 0.5.2
Summary: Configuration generator for WRF namelists
Home-page: UNKNOWN
Author: Jared Lewis
Author-email: jared@bodekerscientific.com
License: MIT
Keywords: wrf config generate generator science forecast
Platform: UNKNOWN
Classifier: Development Status :: 4 - Beta
Classifier: Intended Audience :: Science/Research
Classifier: Intended Audience :: System Administrators
Classifier: License :: OSI Approved :: MIT License
Classifier: Programming Language :: Python :: 2
Classifier: Programming Language :: Python :: 3
Classifier: Topic :: Scientific/Engineering :: Atmospheric Science
